{
    "name": "Franco Sorbello",
    "occupation": "Software Developer",
    "location": "Mendoza, Argentina",
    "avatar": "avatar.jpg",
    "pronouns": "he/him",
    "email": "franco.sorbelo@gmail.com",
    "telephone": "+54 261 636 3940",
    "skills": [
        "Javascript / ES6",
        "Node",
        "Git",
        "C#",
        "Java",
        "Python"
    ],
    "languages": [
        {
            "name": "Spanish",
            "level": "native"
        },
        {
            "name": "English",
            "level": "fluent"
        }
    ],
    "social": [
        {
            "name": "Github",
            "user": "@francosorbello",
            "url": "https://github.com/francosorbello/"
        },
        {
            "name": "LinkedIn",
            "user": "@franco-sorbello",
            "url": "https://www.linkedin.com/in/franco-sorbello/"
        }
    ]
}